docs/Makefile
docs/api.rst
docs/atm_transmission_secz1.5_1.6mm.dat
docs/conf.py
docs/extinction.rst
docs/extraction_quickstart.rst
docs/index.rst
docs/make.bat
docs/specphot_standards.rst
docs/terms.rst
docs/_static/logo_icon.ico
docs/_static/logo_icon.png
docs/_static/specreduce.css
docs/_templates/autosummary/base.rst
docs/_templates/autosummary/class.rst
docs/_templates/autosummary/module.rst
docs/mask_treatment/fig_masking_apply.svg
docs/mask_treatment/fig_masking_apply_mask_only.svg
docs/mask_treatment/fig_masking_apply_nan_only.svg
docs/mask_treatment/fig_masking_ignore.svg
docs/mask_treatment/fig_masking_nan_fill.svg
docs/mask_treatment/fig_masking_propagate.svg
docs/mask_treatment/fig_masking_zero_fill.svg
docs/mask_treatment/mask_treatment.rst
docs/process/NIR_MOS_arc.odg
docs/process/NIR_MOS_arc.svg
docs/process/NIR_MOS_flat.odg
docs/process/NIR_MOS_flat.svg
docs/process/NIR_MOS_science.odg
docs/process/NIR_MOS_science.svg
docs/process/NIR_MOS_trace.odg
docs/process/NIR_MOS_trace.svg
docs/process/NIR_arcs.rst
docs/process/NIR_flats.rst
docs/process/NIR_science_data.rst
docs/process/index.rst
docs/wavelength_calibration/wavelength_calibration.rst
licenses/KOSMOS_LICENSE
licenses/LICENSE.rst
specreduce/__init__.py
specreduce/background.py
specreduce/calibration_data.py
specreduce/compat.py
specreduce/conftest.py
specreduce/core.py
specreduce/extract.py
specreduce/fluxcal.py
specreduce/line_matching.py
specreduce/table_utils.py
specreduce/tracing.py
specreduce/version.py
specreduce/wavecal1d.py
specreduce/wavelength_calibration.py
specreduce/wavesol1d.py
specreduce/tests/__init__.py
specreduce/tests/test_background.py
specreduce/tests/test_core.py
specreduce/tests/test_extinction.py
specreduce/tests/test_extract.py
specreduce/tests/test_image_parsing.py
specreduce/tests/test_line_matching.py
specreduce/tests/test_linelists.py
specreduce/tests/test_mask_treatment.py
specreduce/tests/test_specphot_stds.py
specreduce/tests/test_synth_data.py
specreduce-1.7.0.dist-info/METADATA
specreduce-1.7.0.dist-info/WHEEL
specreduce-1.7.0.dist-info/top_level.txt
specreduce-1.7.0.dist-info/RECORD
