Metadata-Version: 2.4
Name: specreduce
Version: 1.7.0
Summary: Astropy coordinated package for Spectroscopic Reductions
Author-email: Astropy Specreduce contributors <astropy-dev@googlegroups.com>
License: Copyright (c) 2017, Astropy-specreduce Developers
Project-URL: Homepage, http://astropy.org/
Project-URL: Repository, https://github.com/astropy/specreduce.git
Project-URL: Documentation, https://specreduce.readthedocs.io/
Requires-Python: >=3.11
Requires-Dist: numpy>=1.24
Requires-Dist: astropy>=5.3
Requires-Dist: scipy>=1.10
Requires-Dist: specutils>=1.9.1
Requires-Dist: matplotlib>=3.10
Requires-Dist: gwcs
Provides-Extra: test
Requires-Dist: pytest-astropy; extra == "test"
Requires-Dist: photutils>=1.0; extra == "test"
Requires-Dist: tox; extra == "test"
Provides-Extra: docs
Requires-Dist: sphinx-astropy; extra == "docs"
Requires-Dist: photutils>=1.0; extra == "docs"
Requires-Dist: synphot; extra == "docs"
Requires-Dist: nbsphinx; extra == "docs"
Requires-Dist: ipykernel; extra == "docs"
Provides-Extra: all
Requires-Dist: photutils>=1.0; extra == "all"
Requires-Dist: synphot; extra == "all"
